{
  "from": {
    "x": 0,
    "y": 0,
    "z": 0
  },
  "to": {
    "x": 1,
    "y": 1,
    "z": 1
  },
  "faces": {
    "up": {
      "texture": "blocks/textures/dirt.png"
    },
    "down": {
      "texture": "blocks/textures/dirt.png"
    },
    "left": {
      "texture": "blocks/textures/dirt.png"
    },
    "right": {
      "texture": "blocks/textures/dirt.png"
    },
    "front": {
      "texture": "blocks/textures/dirt.png"
    },
    "back": {
      "texture": "blocks/textures/dirt.png"
    }
  }
}